README
setup.cfg
setup.py
vmw.ZSI.egg-info/PKG-INFO
vmw.ZSI.egg-info/SOURCES.txt
vmw.ZSI.egg-info/dependency_links.txt
vmw.ZSI.egg-info/entry_points.txt
vmw.ZSI.egg-info/namespace_packages.txt
vmw.ZSI.egg-info/top_level.txt
vmw/ZSI/ServiceContainer.py
vmw/ZSI/ServiceProxy.py
vmw/ZSI/TC.py
vmw/ZSI/TCapache.py
vmw/ZSI/TCcompound.py
vmw/ZSI/TCnumbers.py
vmw/ZSI/TCtimes.py
vmw/ZSI/__init__.py
vmw/ZSI/address.py
vmw/ZSI/auth.py
vmw/ZSI/client.py
vmw/ZSI/digest_auth.py
vmw/ZSI/dispatch.py
vmw/ZSI/fault.py
vmw/ZSI/parse.py
vmw/ZSI/resolvers.py
vmw/ZSI/schema.py
vmw/ZSI/typeinterpreter.py
vmw/ZSI/version.py
vmw/ZSI/writer.py
vmw/ZSI/generate/__init__.py
vmw/ZSI/generate/commands.py
vmw/ZSI/generate/containers.py
vmw/ZSI/generate/pyclass.py
vmw/ZSI/generate/utility.py
vmw/ZSI/generate/wsdl2dispatch.py
vmw/ZSI/generate/wsdl2python.py
vmw/ZSI/twisted/WSresource.py
vmw/ZSI/twisted/WSsecurity.py
vmw/ZSI/twisted/__init__.py
vmw/ZSI/twisted/client.py
vmw/ZSI/twisted/interfaces.py
vmw/ZSI/twisted/reverse.py
vmw/ZSI/twisted/wsgi.py
vmw/ZSI/wstools/MIMEAttachment.py
vmw/ZSI/wstools/Namespaces.py
vmw/ZSI/wstools/TimeoutSocket.py
vmw/ZSI/wstools/UserTuple.py
vmw/ZSI/wstools/Utility.py
vmw/ZSI/wstools/WSDLTools.py
vmw/ZSI/wstools/XMLSchema.py
vmw/ZSI/wstools/XMLname.py
vmw/ZSI/wstools/__init__.py
vmw/ZSI/wstools/c14n.py
vmw/ZSI/wstools/logging.py