Metadata-Version: 1.0
Name: vmw.ZSI
Version: 2.1-a1
Summary: Zolera SOAP Infrastructure -- VMware edition
Home-page: http://pywebsvcs.sf.net/
Author: Rich Salz, et al
Author-email: pywebsvcs-talk@lists.sf.net
License: Python
Platform: UNKNOWN
